README.md
setup.py
tensorbayes/__init__.py
tensorbayes/distributions.py
tensorbayes/nbutils.py
tensorbayes/nputils.py
tensorbayes/tbutils.py
tensorbayes/tfutils.py
tensorbayes/utils.py
tensorbayes.egg-info/PKG-INFO
tensorbayes.egg-info/SOURCES.txt
tensorbayes.egg-info/dependency_links.txt
tensorbayes.egg-info/requires.txt
tensorbayes.egg-info/top_level.txt
tensorbayes/layers/__init__.py
tensorbayes/layers/normalization.py
tensorbayes/layers/sample.py
tensorbayes/layers/simple.py