Metadata-Version: 1.1
Name: tensorbayes
Version: 0.4.0
Summary: Deep Variational Inference in TensorFlow
Home-page: http://www.github.com/RuiShu/tensorbayes
Author: Rui Shu
Author-email: ruishu@stanford.edu
License: MIT
Download-URL: https://github.com/RuiShu/tensorbayes/archive/0.4.0.tar.gz
Platform: UNKNOWN
